{
  "trainingPhrases": [ {
    "parts": [ {
      "text": "loan package",
      "parameterId": "loanpackage",
      "auto": true
    } ],
    "repeatCount": 1,
    "languageCode": "en"
  }, {
    "parts": [ {
      "text": "Loan Package",
      "parameterId": "loanpackage",
      "auto": true
    } ],
    "repeatCount": 1,
    "languageCode": "en"
  }, {
    "parts": [ {
      "text": "Tell me more about ",
      "auto": true
    }, {
      "text": "Loan Packages",
      "parameterId": "loanpackage",
      "auto": true
    } ],
    "repeatCount": 1,
    "languageCode": "en"
  }, {
    "parts": [ {
      "text": "What does a loan package include?",
      "auto": true
    } ],
    "repeatCount": 1,
    "languageCode": "en"
  }, {
    "parts": [ {
      "text": "Where do I see loan packages?",
      "auto": true
    } ],
    "repeatCount": 1,
    "languageCode": "en"
  }, {
    "parts": [ {
      "text": "Can you explain what a loan package is?",
      "auto": true
    } ],
    "repeatCount": 1,
    "languageCode": "en"
  }, {
    "parts": [ {
      "text": "How do I see a loan package?"
    } ],
    "repeatCount": 1,
    "languageCode": "en"
  }, {
    "parts": [ {
      "text": "What is a loan package?",
      "auto": true
    } ],
    "repeatCount": 1,
    "languageCode": "en"
  } ]
}
